wyff/__init__.py
wyff/wyff.py
wyff-0.0.2.dist-info/LICENSE
wyff-0.0.2.dist-info/METADATA
wyff-0.0.2.dist-info/WHEEL
wyff-0.0.2.dist-info/top_level.txt
wyff-0.0.2.dist-info/RECORD
