Metadata-Version: 2.1
Name: wyff
Version: 0.0.2
Summary: my first package
Home-page: http://github.com/wangfeng22
Author: wyf
Author-email: 2246521484@qq.com
License: MIT Licence
Keywords: pip,wyf
Platform: any
